paf_sapgui_tc_zfmta_rar/__init__.py
paf_sapgui_tc_zfmta_rar/_testcase.py
paf_sapgui_tc_zfmta_rar-0.1.0.dist-info/WHEEL
paf_sapgui_tc_zfmta_rar-0.1.0.dist-info/METADATA
paf_sapgui_tc_zfmta_rar-0.1.0.dist-info/RECORD
