Metadata-Version: 2.1
Name: paf-sapgui-tc-zfmta-rar
Version: 0.1.0
Summary: 
Author: Your Name
Author-email: you@example.com
Requires-Python: >=3.10,<4.0
Classifier: Programming Language :: Python :: 3
Classifier: Programming Language :: Python :: 3.10
Requires-Dist: paf_sapgui (>=1.0.18,<2.0.0)
Requires-Dist: paf_sapgui_eltrans (>=1.0.8,<2.0.0)
Requires-Dist: paf_tools (>=0.3.3,<0.4.0)
Requires-Dist: pendulum (>=2.1.2,<3.0.0)
